capalyzer/__init__.py
capalyzer/cli.py
capalyzer/constants.py
capalyzer/packet_builder/__init__.py
capalyzer/packet_builder/api.py
capalyzer/packet_builder/cli.py
capalyzer/packet_builder/summary_table_factory.py
capalyzer/packet_builder/utils.py
capalyzer/packet_builder/sub_factories/__init__.py
capalyzer/packet_builder/sub_factories/amr_factory.py
capalyzer/packet_builder/sub_factories/ave_genome_size_factory.py
capalyzer/packet_builder/sub_factories/constants.py
capalyzer/packet_builder/sub_factories/hmp_comparison_factory.py
capalyzer/packet_builder/sub_factories/macrobes.py
capalyzer/packet_builder/sub_factories/microbe_directory.py
capalyzer/packet_builder/sub_factories/pathway_factory.py
capalyzer/packet_builder/sub_factories/read_proportions.py
capalyzer/packet_builder/sub_factories/read_stats.py
capalyzer/packet_builder/sub_factories/subfactory.py
capalyzer/packet_builder/sub_factories/taxonomy_factory.py
capalyzer/packet_builder/sub_factories/toxonomy_long_form.py
capalyzer/packet_builder/sub_factories/utils.py
capalyzer/packet_parser/__init__.py
capalyzer/packet_parser/annotate_taxa.py
capalyzer/packet_parser/cli.py
capalyzer/packet_parser/data_utils.py
capalyzer/packet_parser/dataframes.py
capalyzer/packet_parser/diversity_metrics.py
capalyzer/packet_parser/longform_parser.py
capalyzer/packet_parser/microbe-directory.csv
capalyzer/packet_parser/normalize.py
capalyzer/packet_parser/taxa_tree.py
capalyzer/packet_parser/experimental/__init__.py
capalyzer/packet_parser/experimental/experimental.py
capalyzer/packet_parser/ncbi_tree/names.dmp.gz
capalyzer/packet_parser/ncbi_tree/nodes.dmp.gz
tests/__init__.py
tests/test_experimental.py
tests/test_ncbi_tree.py
tests/test_packet_builder.py
tests/test_packet_parser.py
capalyzer-2.16.1.dist-info/LICENSE
capalyzer-2.16.1.dist-info/METADATA
capalyzer-2.16.1.dist-info/WHEEL
capalyzer-2.16.1.dist-info/entry_points.txt
capalyzer-2.16.1.dist-info/top_level.txt
capalyzer-2.16.1.dist-info/RECORD
