Metadata-Version: 2.1
Name: capalyzer
Version: 2.16.1
Summary: Parsing functionality for the metasub CAP
Home-page: https://github.com/dcdanko/capalyzer
Author: David C. Danko
Author-email: dcdanko@gmail.com
License: UNKNOWN
Platform: UNKNOWN
Classifier: Intended Audience :: Developers
Classifier: License :: OSI Approved :: MIT License
Classifier: Natural Language :: English
Classifier: Programming Language :: Python :: 3
Requires-Dist: click
Requires-Dist: pandas
Requires-Dist: scipy
Requires-Dist: numpy
Requires-Dist: umap-learn
